hexhamming.cpython-38-aarch64-linux-gnu.so
hexhamming-2.2.3.dist-info/LICENSE
hexhamming-2.2.3.dist-info/METADATA
hexhamming-2.2.3.dist-info/top_level.txt
hexhamming-2.2.3.dist-info/RECORD
hexhamming-2.2.3.dist-info/WHEEL
