Metadata-Version: 2.1
Name: hexhamming
Version: 2.2.3
Summary: Fast Hamming distance calculation for hexadecimal strings
Home-page: https://github.com/mrecachinas/hexhamming.git
Author: Michael Recachinas
Author-email: m.recachinas@gmail.com
License: UNKNOWN
Keywords: hamming distance simd
Platform: UNKNOWN
Classifier: Operating System :: MacOS :: MacOS X
Classifier: Operating System :: POSIX :: Linux
Classifier: Operating System :: Microsoft :: Windows
Classifier: Programming Language :: C
License-File: LICENSE
